teamwork/__init__.py
teamwork/defs.py
teamwork/_async/__init__.py
teamwork/_async/client.py
teamwork/_async/messaging.py
teamwork/_async/user.py
teamwork_python-0.1.0.dist-info/LICENSE
teamwork_python-0.1.0.dist-info/METADATA
teamwork_python-0.1.0.dist-info/WHEEL
teamwork_python-0.1.0.dist-info/top_level.txt
teamwork_python-0.1.0.dist-info/RECORD
