Metadata-Version: 2.1
Name: teamwork-python
Version: 0.1.0
Summary: The python bot-framework SDK for Teamwork (https://teamwork.app)
Author-email: Danny Kok <dannykok1@gmail.com>
Project-URL: Homepage, https://teamwork.app
Project-URL: Repository, https://github.com/dannykok/teamwork-python
Keywords: teamwork,bot-framework,sdk
Classifier: Programming Language :: Python :: 3.10
Classifier: License :: OSI Approved :: MIT License
Classifier: Operating System :: OS Independent
Requires-Python: >=3.10
License-File: LICENSE
Requires-Dist: aiohttp >=3.10.10
Requires-Dist: pydantic >=2.9.2
Provides-Extra: dev
Requires-Dist: pytest ; extra == 'dev'
Requires-Dist: pytest-asyncio ; extra == 'dev'
